Workbook

Sheet Dashboard
A1: FINANCIAL & PROJECT PERFORMANCE DASHBOARD
B3: TOTAL CASH INCOME | C3: TOTAL EXPENSES | D3: NET CASH PROFIT | E3: TOTAL RECEIVABLES | H3: Month Start | I3: Inflow | J3: Outflow
B4: =SUM(Income!F2:F1000) -> 200000 | C4: =SUM(Expenses!F2:F1000) -> 172087.29 | D4: =B4-C4 -> 27912.71 | E4: =SUM('Project Master'!G2:G1000) -> 0 | H4: 45748 | I4: =SUMIFS(Income!$F$2:$F1000, Income!$A$2:$A1000, ">="&$H4, Income!$A$2:$A1000, "<="&EOMONTH($H4,0)) -> 0 | J4: =SUMIFS(Expenses!$F$2:$F1000, Expenses!$A$2:$A1000, ">="&$H4, Expenses!$A$2:$A1000, "<="&EOMONTH($H4,0)) -> 0
H5: 45778 | I5: =SUMIFS(Income!$F$2:$F1000, Income!$A$2:$A1000, ">="&$H5, Income!$A$2:$A1000, "<="&EOMONTH($H5,0)) -> 0 | J5: =SUMIFS(Expenses!$F$2:$F1000, Expenses!$A$2:$A1000, ">="&$H5, Expenses!$A$2:$A1000, "<="&EOMONTH($H5,0)) -> 0
H6: 45809 | I6: =SUMIFS(Income!$F$2:$F1000, Income!$A$2:$A1000, ">="&$H6, Income!$A$2:$A1000, "<="&EOMONTH($H6,0)) -> 0 | J6: =SUMIFS(Expenses!$F$2:$F1000, Expenses!$A$2:$A1000, ">="&$H6, Expenses!$A$2:$A1000, "<="&EOMONTH($H6,0)) -> 0
B7: Project ID | C7: Customer Name | D7: Total Income | E7: Total Expense | F7: Net Profit | H7: 45839 | I7: =SUMIFS(Income!$F$2:$F1000, Income!$A$2:$A1000, ">="&$H7, Income!$A$2:$A1000, "<="&EOMONTH($H7,0)) -> 0 | J7: =SUMIFS(Expenses!$F$2:$F1000, Expenses!$A$2:$A1000, ">="&$H7, Expenses!$A$2:$A1000, "<="&EOMONTH($H7,0)) -> 0
B8: =IFERROR(__xludf.DUMMYFUNCTION("QUERY('Project Master'!A2:B1000, ""SELECT A, B WHERE A IS NOT NULL"", 0)"),"COMMON") -> COMMON | C8: =IFERROR(__xludf.DUMMYFUNCTION("""COMPUTED_VALUE"""),"Common") -> Common | D8: {=IF(LEN(B8:B100), SUMIF(Income!$B$2:$B1000, B8:B100, Income!$F$2:$F1000), "")} -> 0 | E8: {=IF(LEN(B8:B100), SUMIF(Expenses!$B$2:$B1000, B8:B100, Expenses!$F$2:$F1000), "")} -> 2269.3 | F8: {=IF(LEN(D8:D100), D8:D100 - E8:E100, "")} -> -2269.3 | H8: 45870 | I8: =SUMIFS(Income!$F$2:$F1000, Income!$A$2:$A1000, ">="&$H8, Income!$A$2:$A1000, "<="&EOMONTH($H8,0)) -> 0 | J8: =SUMIFS(Expenses!$F$2:$F1000, Expenses!$A$2:$A1000, ">="&$H8, Expenses!$A$2:$A1000, "<="&EOMONTH($H8,0)) -> 0
B9: =IFERROR(__xludf.DUMMYFUNCTION("""COMPUTED_VALUE"""),"PROJ-1") -> PROJ-1 | C9: =IFERROR(__xludf.DUMMYFUNCTION("""COMPUTED_VALUE"""),"Sareeta Prusty") -> Sareeta Prusty | D9: 200000 | E9: 169817.99 | F9: 30182.01 | H9: 45901 | I9: =SUMIFS(Income!$F$2:$F1000, Income!$A$2:$A1000, ">="&$H9, Income!$A$2:$A1000, "<="&EOMONTH($H9,0)) -> 0 | J9: =SUMIFS(Expenses!$F$2:$F1000, Expenses!$A$2:$A1000, ">="&$H9, Expenses!$A$2:$A1000, "<="&EOMONTH($H9,0)) -> 0
B10: =IFERROR(__xludf.DUMMYFUNCTION("""COMPUTED_VALUE"""),"PROJ-2") -> PROJ-2 | C10: =IFERROR(__xludf.DUMMYFUNCTION("""COMPUTED_VALUE"""),"Mr Sharma") -> Mr Sharma | D10: 0 | E10: 0 | F10: 0 | H10: 45931 | I10: =SUMIFS(Income!$F$2:$F1000, Income!$A$2:$A1000, ">="&$H10, Income!$A$2:$A1000, "<="&EOMONTH($H10,0)) -> 200000 | J10: =SUMIFS(Expenses!$F$2:$F1000, Expenses!$A$2:$A1000, ">="&$H10, Expenses!$A$2:$A1000, "<="&EOMONTH($H10,0)) -> 172087.29
H11: 45962 | I11: =SUMIFS(Income!$F$2:$F1000, Income!$A$2:$A1000, ">="&$H11, Income!$A$2:$A1000, "<="&EOMONTH($H11,0)) -> 0 | J11: =SUMIFS(Expenses!$F$2:$F1000, Expenses!$A$2:$A1000, ">="&$H11, Expenses!$A$2:$A1000, "<="&EOMONTH($H11,0)) -> 0
H12: 45992 | I12: =SUMIFS(Income!$F$2:$F1000, Income!$A$2:$A1000, ">="&$H12, Income!$A$2:$A1000, "<="&EOMONTH($H12,0)) -> 0 | J12: =SUMIFS(Expenses!$F$2:$F1000, Expenses!$A$2:$A1000, ">="&$H12, Expenses!$A$2:$A1000, "<="&EOMONTH($H12,0)) -> 0
H13: 46023 | I13: =SUMIFS(Income!$F$2:$F1000, Income!$A$2:$A1000, ">="&$H13, Income!$A$2:$A1000, "<="&EOMONTH($H13,0)) -> 0 | J13: =SUMIFS(Expenses!$F$2:$F1000, Expenses!$A$2:$A1000, ">="&$H13, Expenses!$A$2:$A1000, "<="&EOMONTH($H13,0)) -> 0
H14: 46054 | I14: =SUMIFS(Income!$F$2:$F1000, Income!$A$2:$A1000, ">="&$H14, Income!$A$2:$A1000, "<="&EOMONTH($H14,0)) -> 0 | J14: =SUMIFS(Expenses!$F$2:$F1000, Expenses!$A$2:$A1000, ">="&$H14, Expenses!$A$2:$A1000, "<="&EOMONTH($H14,0)) -> 0
H15: 46082 | I15: =SUMIFS(Income!$F$2:$F1000, Income!$A$2:$A1000, ">="&$H15, Income!$A$2:$A1000, "<="&EOMONTH($H15,0)) -> 0 | J15: =SUMIFS(Expenses!$F$2:$F1000, Expenses!$A$2:$A1000, ">="&$H15, Expenses!$A$2:$A1000, "<="&EOMONTH($H15,0)) -> 0

Sheet Operations
A1: OPERATIONS & SUBSIDY TRACKER
A3: Total Pending Subsidy | B3: =SUMIFS(Income!F:F, Income!D:D, "*Subsidy*") -> 0
A5: MNRE Status | B5: Count of Projects
A6: {=UNIQUE(Settings!C2:C1000)} -> Booking | B6: =IF(A6:A15="", "", COUNTIF('Project Master'!E:E, A6:A15)) -> 0
A7: MNRE Submitted | B7: =IF(A7:A16="", "", COUNTIF('Project Master'!E:E, A7:A16)) -> 0
A8: Loan Applied | B8: =IF(A8:A17="", "", COUNTIF('Project Master'!E:E, A8:A17)) -> 0
A9: Loan Approved | B9: =IF(A9:A18="", "", COUNTIF('Project Master'!E:E, A9:A18)) -> 0
A10: Installation | B10: =IF(A10:A19="", "", COUNTIF('Project Master'!E:E, A10:A19)) -> 0
A11: Net Metering Done | B11: =IF(A11:A20="", "", COUNTIF('Project Master'!E:E, A11:A20)) -> 0
A12: C Subsidy | B12: =IF(A12:A21="", "", COUNTIF('Project Master'!E:E, A12:A21)) -> 0
A13: S Subsidy | B13: =IF(A13:A22="", "", COUNTIF('Project Master'!E:E, A13:A22)) -> 1
B14: =IF(A14:A23="", "", COUNTIF('Project Master'!E:E, A14:A23))
B15: =IF(A15:A24="", "", COUNTIF('Project Master'!E:E, A15:A24))

Sheet Copy of Dashboard
A1: FINANCIAL & PROJECT PERFORMANCE DASHBOARD
B3: TOTAL CASH INCOME | C3: TOTAL EXPENSES | D3: NET CASH PROFIT | E3: TOTAL RECEIVABLES | H3: Month Start | I3: Inflow | J3: Outflow
B4: =SUM(Income!F2:F1000) -> 200000 | C4: =SUM(Expenses!F2:F1000) -> 172087.29 | D4: =B4-C4 -> 27912.71 | E4: =SUM('Project Master'!G2:G1000) -> 0 | H4: 45748 | I4: =SUMIFS(Income!$F$2:$F1000, Income!$A$2:$A1000, ">="&$H4, Income!$A$2:$A1000, "<="&EOMONTH($H4,0)) -> 0 | J4: =SUMIFS(Expenses!$F$2:$F1000, Expenses!$A$2:$A1000, ">="&$H4, Expenses!$A$2:$A1000, "<="&EOMONTH($H4,0)) -> 0
H5: 45778 | I5: =SUMIFS(Income!$F$2:$F1000, Income!$A$2:$A1000, ">="&$H5, Income!$A$2:$A1000, "<="&EOMONTH($H5,0)) -> 0 | J5: =SUMIFS(Expenses!$F$2:$F1000, Expenses!$A$2:$A1000, ">="&$H5, Expenses!$A$2:$A1000, "<="&EOMONTH($H5,0)) -> 0
H6: 45809 | I6: =SUMIFS(Income!$F$2:$F1000, Income!$A$2:$A1000, ">="&$H6, Income!$A$2:$A1000, "<="&EOMONTH($H6,0)) -> 0 | J6: =SUMIFS(Expenses!$F$2:$F1000, Expenses!$A$2:$A1000, ">="&$H6, Expenses!$A$2:$A1000, "<="&EOMONTH($H6,0)) -> 0
B7: Project ID | C7: Customer Name | D7: Total Income | E7: Total Expense | F7: Net Profit | H7: 45839 | I7: =SUMIFS(Income!$F$2:$F1000, Income!$A$2:$A1000, ">="&$H7, Income!$A$2:$A1000, "<="&EOMONTH($H7,0)) -> 0 | J7: =SUMIFS(Expenses!$F$2:$F1000, Expenses!$A$2:$A1000, ">="&$H7, Expenses!$A$2:$A1000, "<="&EOMONTH($H7,0)) -> 0
B8: =IFERROR(__xludf.DUMMYFUNCTION("QUERY('Project Master'!A2:B1000, ""SELECT A, B WHERE A IS NOT NULL"", 0)"),"COMMON") -> COMMON | C8: =IFERROR(__xludf.DUMMYFUNCTION("""COMPUTED_VALUE"""),"Common") -> Common | D8: {=IF(LEN(B8:B100), SUMIF(Income!$B$2:$B1000, B8:B100, Income!$F$2:$F1000), "")} -> 0 | E8: {=IF(LEN(B8:B100), SUMIF(Expenses!$B$2:$B1000, B8:B100, Expenses!$F$2:$F1000), "")} -> 2269.3 | F8: {=IF(LEN(D8:D100), D8:D100 - E8:E100, "")} -> -2269.3 | H8: 45870 | I8: =SUMIFS(Income!$F$2:$F1000, Income!$A$2:$A1000, ">="&$H8, Income!$A$2:$A1000, "<="&EOMONTH($H8,0)) -> 0 | J8: =SUMIFS(Expenses!$F$2:$F1000, Expenses!$A$2:$A1000, ">="&$H8, Expenses!$A$2:$A1000, "<="&EOMONTH($H8,0)) -> 0
B9: =IFERROR(__xludf.DUMMYFUNCTION("""COMPUTED_VALUE"""),"PROJ-1") -> PROJ-1 | C9: =IFERROR(__xludf.DUMMYFUNCTION("""COMPUTED_VALUE"""),"Sareeta Prusty") -> Sareeta Prusty | D9: 200000 | E9: 169817.99 | F9: 30182.01 | H9: 45901 | I9: =SUMIFS(Income!$F$2:$F1000, Income!$A$2:$A1000, ">="&$H9, Income!$A$2:$A1000, "<="&EOMONTH($H9,0)) -> 0 | J9: =SUMIFS(Expenses!$F$2:$F1000, Expenses!$A$2:$A1000, ">="&$H9, Expenses!$A$2:$A1000, "<="&EOMONTH($H9,0)) -> 0
B10: =IFERROR(__xludf.DUMMYFUNCTION("""COMPUTED_VALUE"""),"PROJ-2") -> PROJ-2 | C10: =IFERROR(__xludf.DUMMYFUNCTION("""COMPUTED_VALUE"""),"Mr Sharma") -> Mr Sharma | D10: 0 | E10: 0 | F10: 0 | H10: 45931 | I10: =SUMIFS(Income!$F$2:$F1000, Income!$A$2:$A1000, ">="&$H10, Income!$A$2:$A1000, "<="&EOMONTH($H10,0)) -> 200000 | J10: =SUMIFS(Expenses!$F$2:$F1000, Expenses!$A$2:$A1000, ">="&$H10, Expenses!$A$2:$A1000, "<="&EOMONTH($H10,0)) -> 172087.29
H11: 45962 | I11: =SUMIFS(Income!$F$2:$F1000, Income!$A$2:$A1000, ">="&$H11, Income!$A$2:$A1000, "<="&EOMONTH($H11,0)) -> 0 | J11: =SUMIFS(Expenses!$F$2:$F1000, Expenses!$A$2:$A1000, ">="&$H11, Expenses!$A$2:$A1000, "<="&EOMONTH($H11,0)) -> 0
H12: 45992 | I12: =SUMIFS(Income!$F$2:$F1000, Income!$A$2:$A1000, ">="&$H12, Income!$A$2:$A1000, "<="&EOMONTH($H12,0)) -> 0 | J12: =SUMIFS(Expenses!$F$2:$F1000, Expenses!$A$2:$A1000, ">="&$H12, Expenses!$A$2:$A1000, "<="&EOMONTH($H12,0)) -> 0
H13: 46023 | I13: =SUMIFS(Income!$F$2:$F1000, Income!$A$2:$A1000, ">="&$H13, Income!$A$2:$A1000, "<="&EOMONTH($H13,0)) -> 0 | J13: =SUMIFS(Expenses!$F$2:$F1000, Expenses!$A$2:$A1000, ">="&$H13, Expenses!$A$2:$A1000, "<="&EOMONTH($H13,0)) -> 0
H14: 46054 | I14: =SUMIFS(Income!$F$2:$F1000, Income!$A$2:$A1000, ">="&$H14, Income!$A$2:$A1000, "<="&EOMONTH($H14,0)) -> 0 | J14: =SUMIFS(Expenses!$F$2:$F1000, Expenses!$A$2:$A1000, ">="&$H14, Expenses!$A$2:$A1000, "<="&EOMONTH($H14,0)) -> 0
H15: 46082 | I15: =SUMIFS(Income!$F$2:$F1000, Income!$A$2:$A1000, ">="&$H15, Income!$A$2:$A1000, "<="&EOMONTH($H15,0)) -> 0 | J15: =SUMIFS(Expenses!$F$2:$F1000, Expenses!$A$2:$A1000, ">="&$H15, Expenses!$A$2:$A1000, "<="&EOMONTH($H15,0)) -> 0

Sheet Project Master
A1: Project ID | B1: Customer Name | C1: Deal Value | D1: Funding Type | E1: MNRE Status | F1: Total Received | G1: Balance Due
A2: COMMON | B2: Common
A3: PROJ-1 | B3: Sareeta Prusty | C3: 200000 | D3: Self-Funded | E3: S Subsidy | F3: =IF(A3="", "", SUMIF(Income!B:B, A3, Income!F:F)) -> 200000 | G3: =IF(A3="", "", C3-F3) -> 0
A4: PROJ-2 | B4: Mr Sharma | F4: =IF(A4="", "", SUMIF(Income!B:B, A4, Income!F:F)) -> 0 | G4: =IF(A4="", "", C4-F4) -> 0
F5: =IF(A5="", "", SUMIF(Income!B:B, A5, Income!F:F)) | G5: =IF(A5="", "", C5-F5)
F6: =IF(A6="", "", SUMIF(Income!B:B, A6, Income!F:F)) | G6: =IF(A6="", "", C6-F6)
F7: =IF(A7="", "", SUMIF(Income!B:B, A7, Income!F:F)) | G7: =IF(A7="", "", C7-F7)
F8: =IF(A8="", "", SUMIF(Income!B:B, A8, Income!F:F)) | G8: =IF(A8="", "", C8-F8)
F9: =IF(A9="", "", SUMIF(Income!B:B, A9, Income!F:F)) | G9: =IF(A9="", "", C9-F9)
F10: =IF(A10="", "", SUMIF(Income!B:B, A10, Income!F:F)) | G10: =IF(A10="", "", C10-F10)
F11: =IF(A11="", "", SUMIF(Income!B:B, A11, Income!F:F)) | G11: =IF(A11="", "", C11-F11)
F12: =IF(A12="", "", SUMIF(Income!B:B, A12, Income!F:F)) | G12: =IF(A12="", "", C12-F12)
F13: =IF(A13="", "", SUMIF(Income!B:B, A13, Income!F:F)) | G13: =IF(A13="", "", C13-F13)
F14: =IF(A14="", "", SUMIF(Income!B:B, A14, Income!F:F)) | G14: =IF(A14="", "", C14-F14)
F15: =IF(A15="", "", SUMIF(Income!B:B, A15, Income!F:F)) | G15: =IF(A15="", "", C15-F15)
F16: =IF(A16="", "", SUMIF(Income!B:B, A16, Income!F:F)) | G16: =IF(A16="", "", C16-F16)
... F101: =IF(A101="", "", SUMIF(Income!B:B, A101, Income!F:F)) | G101: =IF(A101="", "", C101-F101)

Sheet Invoice Tracker
A1: Date | B1: Inv Number | C1: Project ID | D1: Customer Name | E1: Taxable Value | F1: GST (5%) | G1: Total Invoice | H1: Invoice Link
A2: 45952 | B2: SSE1 | C2: PROJ-1 | D2: =IFERROR(VLOOKUP(C2, 'Project Master'!A:B, 2, FALSE), "") -> Sareeta Prusty | E2: 190476.2 | F2: =IF(E2="", "", E2*0.05) -> 9523.81 | G2: =IF(E2="", "", ROUND(E2+F2,0)) -> 200000
D3: =IFERROR(VLOOKUP(C3, 'Project Master'!A:B, 2, FALSE), "") | F3: =IF(E3="", "", E3*0.05) | G3: =IF(E3="", "", E3+F3)
D4: =IFERROR(VLOOKUP(C4, 'Project Master'!A:B, 2, FALSE), "") | F4: =IF(E4="", "", E4*0.05) | G4: =IF(E4="", "", E4+F4)
D5: =IFERROR(VLOOKUP(C5, 'Project Master'!A:B, 2, FALSE), "") | F5: =IF(E5="", "", E5*0.05) | G5: =IF(E5="", "", E5+F5)
D6: =IFERROR(VLOOKUP(C6, 'Project Master'!A:B, 2, FALSE), "") | F6: =IF(E6="", "", E6*0.05) | G6: =IF(E6="", "", E6+F6)
D7: =IFERROR(VLOOKUP(C7, 'Project Master'!A:B, 2, FALSE), "") | F7: =IF(E7="", "", E7*0.05) | G7: =IF(E7="", "", E7+F7)
D8: =IFERROR(VLOOKUP(C8, 'Project Master'!A:B, 2, FALSE), "") | F8: =IF(E8="", "", E8*0.05) | G8: =IF(E8="", "", E8+F8)
D9: =IFERROR(VLOOKUP(C9, 'Project Master'!A:B, 2, FALSE), "") | F9: =IF(E9="", "", E9*0.05) | G9: =IF(E9="", "", E9+F9)
D10: =IFERROR(VLOOKUP(C10, 'Project Master'!A:B, 2, FALSE), "") | F10: =IF(E10="", "", E10*0.05) | G10: =IF(E10="", "", E10+F10)
D11: =IFERROR(VLOOKUP(C11, 'Project Master'!A:B, 2, FALSE), "") | F11: =IF(E11="", "", E11*0.05) | G11: =IF(E11="", "", E11+F11)
D12: =IFERROR(VLOOKUP(C12, 'Project Master'!A:B, 2, FALSE), "") | F12: =IF(E12="", "", E12*0.05) | G12: =IF(E12="", "", E12+F12)
D13: =IFERROR(VLOOKUP(C13, 'Project Master'!A:B, 2, FALSE), "") | F13: =IF(E13="", "", E13*0.05) | G13: =IF(E13="", "", E13+F13)
D14: =IFERROR(VLOOKUP(C14, 'Project Master'!A:B, 2, FALSE), "") | F14: =IF(E14="", "", E14*0.05) | G14: =IF(E14="", "", E14+F14)
... D100: =IFERROR(VLOOKUP(C100, 'Project Master'!A:B, 2, FALSE), "") | F100: =IF(E100="", "", E100*0.05) | G100: =IF(E100="", "", E100+F100)
D101: =IFERROR(VLOOKUP(C101, 'Project Master'!A:B, 2, FALSE), "") | F101: =IF(E101="", "", E101*0.05)
D102: =IFERROR(VLOOKUP(C102, 'Project Master'!A:B, 2, FALSE), "") | F102: =IF(E102="", "", E102*0.05)
D103: =IFERROR(VLOOKUP(C103, 'Project Master'!A:B, 2, FALSE), "") | F103: =IF(E103="", "", E103*0.05)
D104: =IFERROR(VLOOKUP(C104, 'Project Master'!A:B, 2, FALSE), "") | F104: =IF(E104="", "", E104*0.05)
D105: =IFERROR(VLOOKUP(C105, 'Project Master'!A:B, 2, FALSE), "") | F105: =IF(E105="", "", E105*0.05)
D106: =IFERROR(VLOOKUP(C106, 'Project Master'!A:B, 2, FALSE), "") | F106: =IF(E106="", "", E106*0.05)
D107: =IFERROR(VLOOKUP(C107, 'Project Master'!A:B, 2, FALSE), "") | F107: =IF(E107="", "", E107*0.05)
D108: =IFERROR(VLOOKUP(C108, 'Project Master'!A:B, 2, FALSE), "") | F108: =IF(E108="", "", E108*0.05)
D109: =IFERROR(VLOOKUP(C109, 'Project Master'!A:B, 2, FALSE), "") | F109: =IF(E109="", "", E109*0.05)
D110: =IFERROR(VLOOKUP(C110, 'Project Master'!A:B, 2, FALSE), "") | F110: =IF(E110="", "", E110*0.05)
D111: =IFERROR(VLOOKUP(C111, 'Project Master'!A:B, 2, FALSE), "") | F111: =IF(E111="", "", E111*0.05)
D112: =IFERROR(VLOOKUP(C112, 'Project Master'!A:B, 2, FALSE), "") | F112: =IF(E112="", "", E112*0.05)
... D1000: =IFERROR(VLOOKUP(C1000, 'Project Master'!A:B, 2, FALSE), "") | F1000: =IF(E1000="", "", E1000*0.05)

Sheet Income
A1: Date | B1: Project ID | C1: Received From | D1: Category | E1: Mode | F1: Amount | G1: Account
A2: 45948 | B2: PROJ-1 | C2: =IFERROR(VLOOKUP(B2, 'Project Master'!A:B, 2, FALSE), "") -> Sareeta Prusty | D2: Booking Advance | E2: Cash | F2: 10000 | G2: Cash
A3: 45951 | B3: PROJ-1 | C3: =IFERROR(VLOOKUP(B3, 'Project Master'!A:B, 2, FALSE), "") -> Sareeta Prusty | D3: Final Settlement (Customer) | E3: Cheque | F3: 190000 | G3: UCO Bank
C4: =IFERROR(VLOOKUP(B4, 'Project Master'!A:B, 2, FALSE), "") | F4: 0
C5: =IFERROR(VLOOKUP(B5, 'Project Master'!A:B, 2, FALSE), "") | F5: 0
C6: =IFERROR(VLOOKUP(B6, 'Project Master'!A:B, 2, FALSE), "") | F6: 0
C7: =IFERROR(VLOOKUP(B7, 'Project Master'!A:B, 2, FALSE), "") | F7: 0
C8: =IFERROR(VLOOKUP(B8, 'Project Master'!A:B, 2, FALSE), "") | F8: 0
C9: =IFERROR(VLOOKUP(B9, 'Project Master'!A:B, 2, FALSE), "") | F9: 0
C10: =IFERROR(VLOOKUP(B10, 'Project Master'!A:B, 2, FALSE), "") | F10: 0
C11: =IFERROR(VLOOKUP(B11, 'Project Master'!A:B, 2, FALSE), "") | F11: 0
C12: =IFERROR(VLOOKUP(B12, 'Project Master'!A:B, 2, FALSE), "") | F12: 0
C13: =IFERROR(VLOOKUP(B13, 'Project Master'!A:B, 2, FALSE), "") | F13: 0
C14: =IFERROR(VLOOKUP(B14, 'Project Master'!A:B, 2, FALSE), "") | F14: 0
C15: =IFERROR(VLOOKUP(B15, 'Project Master'!A:B, 2, FALSE), "") | F15: 0
... C531: =IFERROR(VLOOKUP(B531, 'Project Master'!A:B, 2, FALSE), "") | F531: 0
F532: 0

Sheet Expenses
A1: Date | B1: Project ID | C1: Vendor | D1: Description | E1: Category | F1: Total Paid | G1: GST % | H1: GST Amount | I1: Taxable Value | J1: Account | K1: Invoice Number
A2: 45950 | B2: PROJ-1 | C2: Solotech Energy | D2: Adani 3kW Solar Kit | E2: Solar Kit | F2: 146633.99 | G2: 5 | H2: {=IF(F2:F1001="", "", F2:F1001 - I2:I1001)} -> 6982.571 | I2: {=IF(F2:F1001="", "", F2:F1001 / (1 + (G2:G1001/100)))} -> 139651.42 | J2: UCO Bank | K2: 537
A3: 45951 | B3: PROJ-1 | C3: Civil Material | D3: Civil Material | E3: Raw Material | F3: 1500 | G3: 0 | H3: 0 | I3: 1500 | J3: Cash
A4: 45951 | B4: PROJ-1 | C4: Sudip | D4: Labour | E4: Labour - Installation | F4: 15500 | G4: 0 | H4: 0 | I4: 15500 | J4: Cash
A5: 45951 | B5: PROJ-1 | C5: TPWODL | D5: Paid by Dinesh PhonePe | E5: Net Metering Fees | F5: 4434 | G5: 0 | H5: 0 | I5: 4434 | J5: UCO Bank
A6: 45951 | B6: PROJ-1 | C6: Electrical Shop | D6: MCB - PhonePe dibya | E6: Raw Material | F6: 850 | G6: 0 | H6: 0 | I6: 850 | J6: UCO Bank
A7: 45951 | B7: PROJ-1 | C7: Electrical Shop | D7: JE Pipe | E7: Raw Material | F7: 900 | G7: 0 | H7: 0 | I7: 900 | J7: Cash | K7: FR/6697
A8: 45960 | B8: COMMON | C8: Jio Fiber | D8: Internet Bill | E8: Office Expenses | F8: 500 | G8: 0 | H8: 0 | I8: 500 | J8: UCO Bank
A9: 45960 | B9: COMMON | C9: TPWODL | D9: Electric Bill | E9: Office Expenses | F9: 269.3 | G9: 0 | H9: 0 | I9: 269.3 | J9: UCO Bank
A10: 45960 | B10: COMMON | D10: Staff Salary | E10: Salary | F10: 1500 | G10: 0 | H10: 0 | I10: 1500 | J10: UCO Bank
F11: 0 | H11: 0 | I11: 0
F12: 0 | H12: 0 | I12: 0
F13: 0 | H13: 0 | I13: 0
F14: 0 | H14: 0 | I14: 0
F15: 0 | H15: 0 | I15: 0
F16: 0 | H16: 0 | I16: 0
F17: 0 | H17: 0 | I17: 0
F18: 0 | H18: 0 | I18: 0
F19: 0 | H19: 0 | I19: 0
F20: 0 | H20: 0 | I20: 0
F21: 0 | H21: 0 | I21: 0
F22: 0 | H22: 0 | I22: 0
... F1001: 0 | H1001: 0 | I1001: 0

Sheet GST Summary
A1: Month | B1: Output Tax (Sales) | C1: Input Tax (Purchase) | D1: Net GST Payable
A2: 45772 | B2: {=SUMIFS('Invoice Tracker'!$F$2:$F1000, TEXT('Invoice Tracker'!$A$2:$A1000,"MMM-yy"), A2:A13)} -> 0 | C2: {=SUMIFS(Expenses!$H$2:$H1000, TEXT(Expenses!$A$2:$A1000,"MMM-yy"), A2:A13)} -> 0 | D2: =B2:B13 - C2:C13 -> 0
A3: 45802 | B3: {=SUMIFS('Invoice Tracker'!$F$2:$F1000, TEXT('Invoice Tracker'!$A$2:$A1000,"MMM-yy"), A3:A14)} -> 0 | C3: {=SUMIFS(Expenses!$H$2:$H1000, TEXT(Expenses!$A$2:$A1000,"MMM-yy"), A3:A14)} -> 0 | D3: =B3:B14 - C3:C14 -> 0
A4: 45833 | B4: {=SUMIFS('Invoice Tracker'!$F$2:$F1000, TEXT('Invoice Tracker'!$A$2:$A1000,"MMM-yy"), A4:A15)} -> 0 | C4: {=SUMIFS(Expenses!$H$2:$H1000, TEXT(Expenses!$A$2:$A1000,"MMM-yy"), A4:A15)} -> 0 | D4: =B4:B15 - C4:C15 -> 0
A5: 45863 | B5: {=SUMIFS('Invoice Tracker'!$F$2:$F1000, TEXT('Invoice Tracker'!$A$2:$A1000,"MMM-yy"), A5:A16)} -> 0 | C5: {=SUMIFS(Expenses!$H$2:$H1000, TEXT(Expenses!$A$2:$A1000,"MMM-yy"), A5:A16)} -> 0 | D5: =B5:B16 - C5:C16 -> 0
A6: 45894 | B6: {=SUMIFS('Invoice Tracker'!$F$2:$F1000, TEXT('Invoice Tracker'!$A$2:$A1000,"MMM-yy"), A6:A17)} -> 0 | C6: {=SUMIFS(Expenses!$H$2:$H1000, TEXT(Expenses!$A$2:$A1000,"MMM-yy"), A6:A17)} -> 0 | D6: =B6:B17 - C6:C17 -> 0
A7: 45925 | B7: {=SUMIFS('Invoice Tracker'!$F$2:$F1000, TEXT('Invoice Tracker'!$A$2:$A1000,"MMM-yy"), A7:A18)} -> 0 | C7: {=SUMIFS(Expenses!$H$2:$H1000, TEXT(Expenses!$A$2:$A1000,"MMM-yy"), A7:A18)} -> 0 | D7: =B7:B18 - C7:C18 -> 0
A8: 45955 | B8: {=SUMIFS('Invoice Tracker'!$F$2:$F1000, TEXT('Invoice Tracker'!$A$2:$A1000,"MMM-yy"), A8:A19)} -> 9523.81 | C8: {=SUMIFS(Expenses!$H$2:$H1000, TEXT(Expenses!$A$2:$A1000,"MMM-yy"), A8:A19)} -> 6982.571 | D8: =B8:B19 - C8:C19 -> 2541.239
A9: 45986 | B9: {=SUMIFS('Invoice Tracker'!$F$2:$F1000, TEXT('Invoice Tracker'!$A$2:$A1000,"MMM-yy"), A9:A20)} -> 0 | C9: {=SUMIFS(Expenses!$H$2:$H1000, TEXT(Expenses!$A$2:$A1000,"MMM-yy"), A9:A20)} -> 0 | D9: =B9:B20 - C9:C20 -> 0
A10: 46016 | B10: {=SUMIFS('Invoice Tracker'!$F$2:$F1000, TEXT('Invoice Tracker'!$A$2:$A1000,"MMM-yy"), A10:A21)} -> 0 | C10: {=SUMIFS(Expenses!$H$2:$H1000, TEXT(Expenses!$A$2:$A1000,"MMM-yy"), A10:A21)} -> 0 | D10: =B10:B21 - C10:C21 -> 0
A11: 45683 | B11: {=SUMIFS('Invoice Tracker'!$F$2:$F1000, TEXT('Invoice Tracker'!$A$2:$A1000,"MMM-yy"), A11:A22)} -> 0 | C11: {=SUMIFS(Expenses!$H$2:$H1000, TEXT(Expenses!$A$2:$A1000,"MMM-yy"), A11:A22)} -> 0 | D11: =B11:B22 - C11:C22 -> 0
A12: 45714 | B12: {=SUMIFS('Invoice Tracker'!$F$2:$F1000, TEXT('Invoice Tracker'!$A$2:$A1000,"MMM-yy"), A12:A23)} -> 0 | C12: {=SUMIFS(Expenses!$H$2:$H1000, TEXT(Expenses!$A$2:$A1000,"MMM-yy"), A12:A23)} -> 0 | D12: =B12:B23 - C12:C23 -> 0
A13: 45742 | B13: {=SUMIFS('Invoice Tracker'!$F$2:$F1000, TEXT('Invoice Tracker'!$A$2:$A1000,"MMM-yy"), A13:A24)} -> 0 | C13: {=SUMIFS(Expenses!$H$2:$H1000, TEXT(Expenses!$A$2:$A1000,"MMM-yy"), A13:A24)} -> 0 | D13: =B13:B24 - C13:C24 -> 0
A14: FY 25-26 TOTAL | B14: =SUM(B2:B13) -> 9523.81 | C14: =SUM(C2:C13) -> 6982.571 | D14: =SUM(D2:D13) -> 2541.239

Sheet Bank balances
A1: BANK BALANCES & LIQUIDITY SNAPSHOT
A3: Account Name | B3: Total In (+) | C3: Total Out (-) | D3: Current Balance
A4: {=UNIQUE(Settings!B2:B1000)} -> Cash | B4: =IF(A4:A10="", "", SUMIF(Income!G:G, A4:A10, Income!F:F)) -> 10000 | C4: =IF(A4:A10="", "", SUMIF(Expenses!J:J, A4:A10, Expenses!F:F)) -> 17900 | D4: =B4:B10 - C4:C10 -> -7900
A5: UCO Bank | B5: =IF(A5:A11="", "", SUMIF(Income!G:G, A5:A11, Income!F:F)) -> 190000 | C5: =IF(A5:A11="", "", SUMIF(Expenses!J:J, A5:A11, Expenses!F:F)) -> 154187.29 | D5: =B5:B11 - C5:C11 -> 35812.71
A6: IDFC Bank | B6: =IF(A6:A12="", "", SUMIF(Income!G:G, A6:A12, Income!F:F)) -> 0 | C6: =IF(A6:A12="", "", SUMIF(Expenses!J:J, A6:A12, Expenses!F:F)) -> 0 | D6: =B6:B12 - C6:C12 -> 0
B7: =IF(A7:A13="", "", SUMIF(Income!G:G, A7:A13, Income!F:F)) | C7: =IF(A7:A13="", "", SUMIF(Expenses!J:J, A7:A13, Expenses!F:F)) | D7: =B7:B13 - C7:C13 -> 0
B8: =IF(A8:A14="", "", SUMIF(Income!G:G, A8:A14, Income!F:F)) | C8: =IF(A8:A14="", "", SUMIF(Expenses!J:J, A8:A14, Expenses!F:F)) | D8: =B8:B14 - C8:C14 -> 0
B9: =IF(A9:A15="", "", SUMIF(Income!G:G, A9:A15, Income!F:F)) | C9: =IF(A9:A15="", "", SUMIF(Expenses!J:J, A9:A15, Expenses!F:F)) | D9: =B9:B15 - C9:C15 -> 0
B10: =IF(A10:A16="", "", SUMIF(Income!G:G, A10:A16, Income!F:F)) | C10: =IF(A10:A16="", "", SUMIF(Expenses!J:J, A10:A16, Expenses!F:F)) | D10: =B10:B16 - C10:C16 -> 0

Sheet Bank Statement
A1: Select Account: | B1: UCO Bank | C1: Opening Balance: | D1: 0 | E1: Total Income: | F1: =SUM(D4:D1000) -> 190000 | G1: Total Expense: | H1: =SUM(E4:E1000) -> 154187.29 | I1: Current Balance: | J1: =D1 + F1 - H1 -> 35812.71
A3: Date | B3: Description / Vendor | C3: Category | D3: Income (+) | E3: Expense (-) | F3: Running Balance
A4: =IFERROR(__xludf.DUMMYFUNCTION("IF(B1="""", ""Please select an account above"", SORT({ QUERY(Income!A2:G1000, ""SELECT A, C, D, F, 0 WHERE G = '""&B1&""' AND A IS NOT NULL"", 0); QUERY(Expenses!A2:J1000, ""SELECT A, C, E, 0, F WHERE J = '""&B1&""' AND A IS NOT NULL"", 0) }, 1, TRUE)"&")"),45950.0) -> 45950 | B4: =IFERROR(__xludf.DUMMYFUNCTION("""COMPUTED_VALUE"""),"Solotech Energy") -> Solotech Energy | C4: =IFERROR(__xludf.DUMMYFUNCTION("""COMPUTED_VALUE"""),"Solar Kit") -> Solar Kit | D4: =IFERROR(__xludf.DUMMYFUNCTION("""COMPUTED_VALUE"""),0.0) -> 0 | E4: =IFERROR(__xludf.DUMMYFUNCTION("""COMPUTED_VALUE"""),146633.99) -> 146633.99 | F4: =IF(A4="", "", D1 + D4 - E4) -> -146633.99
A5: =IFERROR(__xludf.DUMMYFUNCTION("""COMPUTED_VALUE"""),45951.0) -> 45951 | B5: =IFERROR(__xludf.DUMMYFUNCTION("""COMPUTED_VALUE"""),"Sareeta Prusty") -> Sareeta Prusty | C5: =IFERROR(__xludf.DUMMYFUNCTION("""COMPUTED_VALUE"""),"Final Settlement (Customer)") -> Final Settlement (Customer) | D5: =IFERROR(__xludf.DUMMYFUNCTION("""COMPUTED_VALUE"""),190000.0) -> 190000 | E5: =IFERROR(__xludf.DUMMYFUNCTION("""COMPUTED_VALUE"""),0.0) -> 0 | F5: =IF(A5="", "", F4 + D5 - E5) -> 43366.01
A6: =IFERROR(__xludf.DUMMYFUNCTION("""COMPUTED_VALUE"""),45951.0) -> 45951 | B6: =IFERROR(__xludf.DUMMYFUNCTION("""COMPUTED_VALUE"""),"TPWODL") -> TPWODL | C6: =IFERROR(__xludf.DUMMYFUNCTION("""COMPUTED_VALUE"""),"Net Metering Fees") -> Net Metering Fees | D6: =IFERROR(__xludf.DUMMYFUNCTION("""COMPUTED_VALUE"""),0.0) -> 0 | E6: =IFERROR(__xludf.DUMMYFUNCTION("""COMPUTED_VALUE"""),4434.0) -> 4434 | F6: =IF(A6="", "", F5 + D6 - E6) -> 38932.01
A7: =IFERROR(__xludf.DUMMYFUNCTION("""COMPUTED_VALUE"""),45951.0) -> 45951 | B7: =IFERROR(__xludf.DUMMYFUNCTION("""COMPUTED_VALUE"""),"Electrical Shop") -> Electrical Shop | C7: =IFERROR(__xludf.DUMMYFUNCTION("""COMPUTED_VALUE"""),"Raw Material") -> Raw Material | D7: =IFERROR(__xludf.DUMMYFUNCTION("""COMPUTED_VALUE"""),0.0) -> 0 | E7: =IFERROR(__xludf.DUMMYFUNCTION("""COMPUTED_VALUE"""),850.0) -> 850 | F7: =IF(A7="", "", F6 + D7 - E7) -> 38082.01
A8: =IFERROR(__xludf.DUMMYFUNCTION("""COMPUTED_VALUE"""),45960.0) -> 45960 | B8: =IFERROR(__xludf.DUMMYFUNCTION("""COMPUTED_VALUE"""),"Jio Fiber") -> Jio Fiber | C8: =IFERROR(__xludf.DUMMYFUNCTION("""COMPUTED_VALUE"""),"Office Expenses") -> Office Expenses | D8: =IFERROR(__xludf.DUMMYFUNCTION("""COMPUTED_VALUE"""),0.0) -> 0 | E8: =IFERROR(__xludf.DUMMYFUNCTION("""COMPUTED_VALUE"""),500.0) -> 500 | F8: =IF(A8="", "", F7 + D8 - E8) -> 37582.01
A9: =IFERROR(__xludf.DUMMYFUNCTION("""COMPUTED_VALUE"""),45960.0) -> 45960 | B9: =IFERROR(__xludf.DUMMYFUNCTION("""COMPUTED_VALUE"""),"TPWODL") -> TPWODL | C9: =IFERROR(__xludf.DUMMYFUNCTION("""COMPUTED_VALUE"""),"Office Expenses") -> Office Expenses | D9: =IFERROR(__xludf.DUMMYFUNCTION("""COMPUTED_VALUE"""),0.0) -> 0 | E9: =IFERROR(__xludf.DUMMYFUNCTION("""COMPUTED_VALUE"""),269.3) -> 269.3 | F9: =IF(A9="", "", F8 + D9 - E9) -> 37312.71
A10: =IFERROR(__xludf.DUMMYFUNCTION("""COMPUTED_VALUE"""),45960.0) -> 45960 | C10: =IFERROR(__xludf.DUMMYFUNCTION("""COMPUTED_VALUE"""),"Salary") -> Salary | D10: =IFERROR(__xludf.DUMMYFUNCTION("""COMPUTED_VALUE"""),0.0) -> 0 | E10: =IFERROR(__xludf.DUMMYFUNCTION("""COMPUTED_VALUE"""),1500.0) -> 1500 | F10: =IF(A10="", "", F9 + D10 - E10) -> 35812.71
A11: =IFERROR(__xludf.DUMMYFUNCTION("""COMPUTED_VALUE"""),"") | B11: =IFERROR(__xludf.DUMMYFUNCTION("""COMPUTED_VALUE"""),"") | C11: =IFERROR(__xludf.DUMMYFUNCTION("""COMPUTED_VALUE"""),"") | D11: =IFERROR(__xludf.DUMMYFUNCTION("""COMPUTED_VALUE"""),"") | E11: =IFERROR(__xludf.DUMMYFUNCTION("""COMPUTED_VALUE"""),"0()") -> 0() | F11: =IF(A11="", "", F10 + D11 - E11)
A12: =IFERROR(__xludf.DUMMYFUNCTION("""COMPUTED_VALUE"""),"") | B12: =IFERROR(__xludf.DUMMYFUNCTION("""COMPUTED_VALUE"""),"") | C12: =IFERROR(__xludf.DUMMYFUNCTION("""COMPUTED_VALUE"""),"") | D12: =IFERROR(__xludf.DUMMYFUNCTION("""COMPUTED_VALUE"""),"0()") -> 0() | E12: =IFERROR(__xludf.DUMMYFUNCTION("""COMPUTED_VALUE"""),"") | F12: =IF(A12="", "", F11 + D12 - E12)
F13: =IF(A13="", "", F12 + D13 - E13)
F14: =IF(A14="", "", F13 + D14 - E14)
F15: =IF(A15="", "", F14 + D15 - E15)
F16: =IF(A16="", "", F15 + D16 - E16)
F17: =IF(A17="", "", F16 + D17 - E17)
F18: =IF(A18="", "", F17 + D18 - E18)
F19: =IF(A19="", "", F18 + D19 - E19)
F20: =IF(A20="", "", F19 + D20 - E20)
F21: =IF(A21="", "", F20 + D21 - E21)
F22: =IF(A22="", "", F21 + D22 - E22)
F23: =IF(A23="", "", F22 + D23 - E23)
F24: =IF(A24="", "", F23 + D24 - E24)
... F1000: =IF(A1000="", "", F999 + D1000 - E1000)

Sheet Settings
A1: Payment Modes | B1: Accounts | C1: MNRE Status | D1: Income Categories | E1: Vendors | F1: GST % | H1: Direct Categories
A2: UPI | B2: Cash | C2: Booking | D2: Booking Advance | E2: Solotech Green Energy | F2: 0 | H2: Solar Kit
A3: Bank Transfer | B3: UCO Bank | C3: MNRE Submitted | D3: Bank Loan (Part) | E3: KD Powers | F3: 5 | H3: Structure & Mounting
A4: Cash | B4: IDFC Bank | C4: Loan Applied | D4: Bank Loan (Final) | F4: 12 | H4: Raw Material
A5: Cheque | C5: Loan Approved | D5: Part Payment (Customer) | F5: 18 | H5: Transportation
C6: Installation | D6: Final Settlement (Customer) | H6: Labour - Installation
C7: Net Metering Done | D7: Net Metering Fee | H7: Net Metering Fees
C8: C Subsidy | H8: Project - Others
C9: S Subsidy | H9: Office Rent
H10: Office Expenses
H11: Salary
H12: Tools & Equipment
H13: Travel & Petrol
H14: Stationery
H15: Professional Fees (CA)
H16: Misc
